py5_layout/__init__.py
py5_layout/background_manager.py
py5_layout/border_manager.py
py5_layout/button.py
py5_layout/color_manager.py
py5_layout/components.py
py5_layout/element.py
py5_layout/layout_manager.py
py5_layout/literal_finder.py
py5_layout/parent_manager.py
py5_layout/py5_layout.py
py5_layout/style.py
py5_layout/text_manager.py
py5_layout-0.1.0.dist-info/LICENSE
py5_layout-0.1.0.dist-info/METADATA
py5_layout-0.1.0.dist-info/WHEEL
py5_layout-0.1.0.dist-info/RECORD
