Metadata-Version: 2.3
Name: py5-layout
Version: 0.1.0
Summary: A layout and styling library for py5
Author: Ty Todd
Author-email: swagginty@gmail.com
Requires-Python: >=3.9
Classifier: Programming Language :: Python :: 3
Classifier: Programming Language :: Python :: 3.9
Classifier: Programming Language :: Python :: 3.10
Classifier: Programming Language :: Python :: 3.11
Classifier: Programming Language :: Python :: 3.12
Classifier: Programming Language :: Python :: 3.13
Requires-Dist: numpy (>=1.26)
Requires-Dist: poga (>=0.1.19,<0.2.0)
Requires-Dist: py5 (>=0.10.6a0,<0.11.0)
Requires-Dist: pytest (>=8.4.1,<9.0.0)
Requires-Dist: webcolors (>=24.11.1,<25.0.0)
Project-URL: Homepage, https://github.com/TyTodd/py5-layout
